<?xml version="1.0" encoding="UTF-8"?>
<repomd xmlns="http://linux.duke.edu/metadata/repo">
  <data type="other">
    <location href="repodata/other.xml.gz"/>
    <checksum type="sha">8270f53cf798cfb786c523c7eb7612eb056b68f6</checksum>
    <timestamp>1481706288</timestamp>
    <open-checksum type="sha">4d418968cad9c8f9198fb9a9e626927c535b71b3</open-checksum>
  </data>
  <data type="filelists">
    <location href="repodata/filelists.xml.gz"/>
    <checksum type="sha">ec8be8ab2d01957fd5a014dbed034ae1f20b0fa5</checksum>
    <timestamp>1481706288</timestamp>
    <open-checksum type="sha">fbdedeca5deb1aa3039e5d80f001e3b531815967</open-checksum>
  </data>
  <data type="primary">
    <location href="repodata/primary.xml.gz"/>
    <checksum type="sha">93f658fee94badf68a12481957fe79c1f9a63901</checksum>
    <timestamp>1481706288</timestamp>
    <open-checksum type="sha">0f5d4fcb44687a42fa742d2cd5882a8cb3f36bd2</open-checksum>
  </data>
</repomd>
